Workbook

Sheet 00_Control
A2: Window_Preset | B2: Custom
A3: Start_Date | B3: =IF(B2="Last 7", TODAY()-7, IF(B2="Last 14", TODAY()-14, IF(B2="Last 30", TODAY()-30, IF(B2="MTD", EOMONTH(TODAY(),-1)+1, IF(B2="Custom", B5,""))))) -> 46037
A4: End_Date | B4: =TODAY() -> 46092
A5: Custom_Start_Date | B5: 46037
A7: Min_Spend | B7: 50
A8: Min_Purchases | B8: 2
A9: Good_ROAS | B9: 2
A10: Bad_ROAS | B10: 1
A11: Good_CPA | B11: 20
A12: Bad_CPA | B12: 40

Sheet 01_Raw_Meta
A1: Date | B1: Campaign | C1: Adset | D1: Ad | E1: Spend | F1: Impressions | G1: Clicks | H1: ATC | I1: Purchases | J1: Purchases Value
A2: 46023 | B2: Campaign_C | C2: Retargeting | D2: Creative_1 | E2: 272.12 | F2: 16338 | G2: 778 | H2: 89 | I2: 5 | J2: 748.97
A3: 46024 | B3: Campaign_A | C3: Retargeting | D3: Creative_3 | E3: 197.27 | F3: 3491 | G3: 1070 | H3: 79 | I3: 38 | J3: 1120.8
A4: 46025 | B4: Campaign_C | C4: Retargeting | D4: Creative_2 | E4: 114.93 | F4: 16328 | G4: 810 | H4: 105 | I4: 3 | J4: 974.23
A5: 46026 | B5: Campaign_C | C5: Prospecting | D5: Creative_1 | E5: 117.78 | F5: 15599 | G5: 725 | H5: 40 | I5: 53 | J5: 1211.06
A6: 46027 | B6: Campaign_A | C6: Prospecting | D6: Creative_1 | E6: 223.27 | F6: 4051 | G6: 506 | H6: 103 | I6: 23 | J6: 860.57
A7: 46028 | B7: Campaign_A | C7: Prospecting | D7: Creative_1 | E7: 271.19 | F7: 16979 | G7: 969 | H7: 23 | I7: 37 | J7: 1425.57
A8: 46029 | B8: Campaign_C | C8: Prospecting | D8: Creative_3 | E8: 268.38 | F8: 17388 | G8: 241 | H8: 24 | I8: 53 | J8: 442.13
A9: 46030 | B9: Campaign_B | C9: Retargeting | D9: Creative_2 | E9: 238.37 | F9: 1876 | G9: 788 | H9: 61 | I9: 37 | J9: 1423.35
A10: 46031 | B10: Campaign_C | C10: Prospecting | D10: Creative_1 | E10: 199.77 | F10: 5142 | G10: 1172 | H10: 22 | I10: 10 | J10: 882.16
A11: 46032 | B11: Campaign_C | C11: Prospecting | D11: Creative_1 | E11: 43.56 | F11: 16202 | G11: 1027 | H11: 51 | I11: 10 | J11: 1761.2
A12: 46033 | B12: Campaign_C | C12: Prospecting | D12: Creative_1 | E12: 65.26 | F12: 7966 | G12: 1058 | H12: 109 | I12: 19 | J12: 1078.95
A13: 46034 | B13: Campaign_C | C13: Prospecting | D13: Creative_3 | E13: 271.6 | F13: 8079 | G13: 145 | H13: 53 | I13: 17 | J13: 1948.91
... A101: 46032 | B101: Campaign_A | C101: Prospecting | D101: Creative_1 | E101: 30.46 | F101: 1412 | G101: 935 | H101: 99 | I101: 48 | J101: 1465.07

Sheet 02_Raw_Google
A1: Date | B1: Campaign | C1: AdGroup | D1: Asset | E1: Spend | F1: Impressions | G1: Clicks | H1: Purchases | I1: Purchase_Value
A2: 46023 | B2: PMax | C2: Group_2 | D2: Headline_A | E2: 74.66 | F2: 6922 | G2: 649 | H2: 26 | I2: 106.17
A3: 46024 | B3: Search_Generic | C3: Group_2 | D3: Headline_C | E3: 61.09 | F3: 1281 | G3: 217 | H3: 3 | I3: 693.78
A4: 46025 | B4: PMax | C4: Group_3 | D4: Headline_A | E4: 133.79 | F4: 953 | G4: 842 | H4: 6 | I4: 1272.97
A5: 46026 | B5: Search_Brand | C5: Group_3 | D5: Headline_A | E5: 154.84 | F5: 8417 | G5: 127 | H5: 5 | I5: 636.85
A6: 46027 | B6: Search_Brand | C6: Group_3 | D6: Headline_A | E6: 94.73 | F6: 2324 | G6: 160 | H6: 5 | I6: 334.89
A7: 46028 | B7: Search_Generic | C7: Group_2 | D7: Headline_B | E7: 148.82 | F7: 2920 | G7: 834 | H7: 23 | I7: 1150.25
A8: 46029 | B8: Search_Generic | C8: Group_3 | D8: Headline_A | E8: 223.55 | F8: 3143 | G8: 200 | H8: 9 | I8: 1200.11
A9: 46030 | B9: Search_Generic | C9: Group_3 | D9: Headline_A | E9: 145.83 | F9: 5936 | G9: 212 | H9: 35 | I9: 326.73
A10: 46031 | B10: PMax | C10: Group_1 | D10: Headline_B | E10: 184.39 | F10: 6560 | G10: 393 | H10: 20 | I10: 1174.61
A11: 46032 | B11: Search_Brand | C11: Group_1 | D11: Headline_A | E11: 204.25 | F11: 2040 | G11: 68 | H11: 35 | I11: 1425.16
A12: 46033 | B12: Search_Brand | C12: Group_2 | D12: Headline_C | E12: 247.35 | F12: 860 | G12: 556 | H12: 18 | I12: 316.26
A13: 46034 | B13: PMax | C13: Group_3 | D13: Headline_C | E13: 156.75 | F13: 9930 | G13: 526 | H13: 17 | I13: 1174.8
... A101: 46032 | B101: PMax | C101: Group_3 | D101: Headline_C | E101: 239.48 | F101: 4023 | G101: 255 | H101: 30 | I101: 890.68

Sheet 03_Raw_Shopify
A1: Date | B1: Order_ID | C1: Product_ID | D1: Product_Title | E1: Quantity | F1: Gross_Sales | G1: Discounts | H1: Refunds | I1: Net_Sales
A2: 46023 | B2: ORD1000 | C2: 178 | D2: Collagen | E2: 3 | F2: 177.71 | G2: 12.76 | H2: 2.24 | I2: 162.71
A3: 46024 | B3: ORD1001 | C3: 179 | D3: Vitamin C | E3: 3 | F3: 93.86 | G3: 5.14 | H3: 9.57 | I3: 79.15
A4: 46025 | B4: ORD1002 | C4: 153 | D4: Collagen | E4: 2 | F4: 80.47 | G4: 12.64 | H4: 5.73 | I4: 62.1
A5: 46026 | B5: ORD1003 | C5: 185 | D5: Magnesium | E5: 1 | F5: 140.34 | G5: 1.17 | H5: 9.33 | I5: 129.84
A6: 46027 | B6: ORD1004 | C6: 191 | D6: Collagen | E6: 1 | F6: 85.82 | G6: 2.84 | H6: 5.75 | I6: 77.23
A7: 46028 | B7: ORD1005 | C7: 119 | D7: Magnesium | E7: 3 | F7: 137.14 | G7: 5.49 | H7: 4.79 | I7: 126.86
A8: 46029 | B8: ORD1006 | C8: 132 | D8: Magnesium | E8: 1 | F8: 133.67 | G8: 11.94 | H8: 3.14 | I8: 118.59
A9: 46030 | B9: ORD1007 | C9: 173 | D9: Magnesium | E9: 1 | F9: 125.78 | G9: 13.52 | H9: 6.06 | I9: 106.2
A10: 46031 | B10: ORD1008 | C10: 139 | D10: Magnesium | E10: 1 | F10: 94.67 | G10: 8.85 | H10: 1.39 | I10: 84.43
A11: 46032 | B11: ORD1009 | C11: 131 | D11: Magnesium | E11: 3 | F11: 123.24 | G11: 8.92 | H11: 8.98 | I11: 105.34
A12: 46033 | B12: ORD1010 | C12: 196 | D12: Vitamin C | E12: 2 | F12: 131.4 | G12: 14.49 | H12: 8.29 | I12: 108.62
A13: 46034 | B13: ORD1011 | C13: 101 | D13: Protein Powder | E13: 2 | F13: 122.77 | G13: 0.32 | H13: 3.18 | I13: 119.27
... A101: 46032 | B101: ORD1099 | C101: 148 | D101: Protein Powder | E101: 3 | F101: 65.05 | G101: 3.08 | H101: 2.79 | I101: 59.18

Sheet 10_Clean_Meta
A1: Date | B1: Channel | C1: Campaign | D1: Adset | E1: Ad | F1: Spend | G1: Impressions | H1: Clicks | I1: AddtoCart | J1: Purchases | K1: Revenue
A2: ='01_Raw_Meta'!A2 -> 46023 | B2: ="Meta" -> Meta | C2: ='01_Raw_Meta'!B2 -> Campaign_C | D2: ='01_Raw_Meta'!C2 -> Retargeting | E2: ='01_Raw_Meta'!D2 -> Creative_1 | F2: ='01_Raw_Meta'!E2 -> 272.12 | G2: ='01_Raw_Meta'!F2 -> 16338 | H2: ='01_Raw_Meta'!G2 -> 778 | I2: ='01_Raw_Meta'!H2 -> 89 | J2: ='01_Raw_Meta'!I2 -> 5 | K2: ='01_Raw_Meta'!J2 -> 748.97
A3: ='01_Raw_Meta'!A3 -> 46024 | B3: ="Meta" -> Meta | C3: ='01_Raw_Meta'!B3 -> Campaign_A | D3: ='01_Raw_Meta'!C3 -> Retargeting | E3: ='01_Raw_Meta'!D3 -> Creative_3 | F3: ='01_Raw_Meta'!E3 -> 197.27 | G3: ='01_Raw_Meta'!F3 -> 3491 | H3: ='01_Raw_Meta'!G3 -> 1070 | I3: ='01_Raw_Meta'!H3 -> 79 | J3: ='01_Raw_Meta'!I3 -> 38 | K3: ='01_Raw_Meta'!J3 -> 1120.8
A4: ='01_Raw_Meta'!A4 -> 46025 | B4: ="Meta" -> Meta | C4: ='01_Raw_Meta'!B4 -> Campaign_C | D4: ='01_Raw_Meta'!C4 -> Retargeting | E4: ='01_Raw_Meta'!D4 -> Creative_2 | F4: ='01_Raw_Meta'!E4 -> 114.93 | G4: ='01_Raw_Meta'!F4 -> 16328 | H4: ='01_Raw_Meta'!G4 -> 810 | I4: ='01_Raw_Meta'!H4 -> 105 | J4: ='01_Raw_Meta'!I4 -> 3 | K4: ='01_Raw_Meta'!J4 -> 974.23
A5: ='01_Raw_Meta'!A5 -> 46026 | B5: ="Meta" -> Meta | C5: ='01_Raw_Meta'!B5 -> Campaign_C | D5: ='01_Raw_Meta'!C5 -> Prospecting | E5: ='01_Raw_Meta'!D5 -> Creative_1 | F5: ='01_Raw_Meta'!E5 -> 117.78 | G5: ='01_Raw_Meta'!F5 -> 15599 | H5: ='01_Raw_Meta'!G5 -> 725 | I5: ='01_Raw_Meta'!H5 -> 40 | J5: ='01_Raw_Meta'!I5 -> 53 | K5: ='01_Raw_Meta'!J5 -> 1211.06
A6: ='01_Raw_Meta'!A6 -> 46027 | B6: ="Meta" -> Meta | C6: ='01_Raw_Meta'!B6 -> Campaign_A | D6: ='01_Raw_Meta'!C6 -> Prospecting | E6: ='01_Raw_Meta'!D6 -> Creative_1 | F6: ='01_Raw_Meta'!E6 -> 223.27 | G6: ='01_Raw_Meta'!F6 -> 4051 | H6: ='01_Raw_Meta'!G6 -> 506 | I6: ='01_Raw_Meta'!H6 -> 103 | J6: ='01_Raw_Meta'!I6 -> 23 | K6: ='01_Raw_Meta'!J6 -> 860.57
A7: ='01_Raw_Meta'!A7 -> 46028 | B7: ="Meta" -> Meta | C7: ='01_Raw_Meta'!B7 -> Campaign_A | D7: ='01_Raw_Meta'!C7 -> Prospecting | E7: ='01_Raw_Meta'!D7 -> Creative_1 | F7: ='01_Raw_Meta'!E7 -> 271.19 | G7: ='01_Raw_Meta'!F7 -> 16979 | H7: ='01_Raw_Meta'!G7 -> 969 | I7: ='01_Raw_Meta'!H7 -> 23 | J7: ='01_Raw_Meta'!I7 -> 37 | K7: ='01_Raw_Meta'!J7 -> 1425.57
A8: ='01_Raw_Meta'!A8 -> 46029 | B8: ="Meta" -> Meta | C8: ='01_Raw_Meta'!B8 -> Campaign_C | D8: ='01_Raw_Meta'!C8 -> Prospecting | E8: ='01_Raw_Meta'!D8 -> Creative_3 | F8: ='01_Raw_Meta'!E8 -> 268.38 | G8: ='01_Raw_Meta'!F8 -> 17388 | H8: ='01_Raw_Meta'!G8 -> 241 | I8: ='01_Raw_Meta'!H8 -> 24 | J8: ='01_Raw_Meta'!I8 -> 53 | K8: ='01_Raw_Meta'!J8 -> 442.13
A9: ='01_Raw_Meta'!A9 -> 46030 | B9: ="Meta" -> Meta | C9: ='01_Raw_Meta'!B9 -> Campaign_B | D9: ='01_Raw_Meta'!C9 -> Retargeting | E9: ='01_Raw_Meta'!D9 -> Creative_2 | F9: ='01_Raw_Meta'!E9 -> 238.37 | G9: ='01_Raw_Meta'!F9 -> 1876 | H9: ='01_Raw_Meta'!G9 -> 788 | I9: ='01_Raw_Meta'!H9 -> 61 | J9: ='01_Raw_Meta'!I9 -> 37 | K9: ='01_Raw_Meta'!J9 -> 1423.35
A10: ='01_Raw_Meta'!A10 -> 46031 | B10: ="Meta" -> Meta | C10: ='01_Raw_Meta'!B10 -> Campaign_C | D10: ='01_Raw_Meta'!C10 -> Prospecting | E10: ='01_Raw_Meta'!D10 -> Creative_1 | F10: ='01_Raw_Meta'!E10 -> 199.77 | G10: ='01_Raw_Meta'!F10 -> 5142 | H10: ='01_Raw_Meta'!G10 -> 1172 | I10: ='01_Raw_Meta'!H10 -> 22 | J10: ='01_Raw_Meta'!I10 -> 10 | K10: ='01_Raw_Meta'!J10 -> 882.16
A11: ='01_Raw_Meta'!A11 -> 46032 | B11: ="Meta" -> Meta | C11: ='01_Raw_Meta'!B11 -> Campaign_C | D11: ='01_Raw_Meta'!C11 -> Prospecting | E11: ='01_Raw_Meta'!D11 -> Creative_1 | F11: ='01_Raw_Meta'!E11 -> 43.56 | G11: ='01_Raw_Meta'!F11 -> 16202 | H11: ='01_Raw_Meta'!G11 -> 1027 | I11: ='01_Raw_Meta'!H11 -> 51 | J11: ='01_Raw_Meta'!I11 -> 10 | K11: ='01_Raw_Meta'!J11 -> 1761.2
A12: ='01_Raw_Meta'!A12 -> 46033 | B12: ="Meta" -> Meta | C12: ='01_Raw_Meta'!B12 -> Campaign_C | D12: ='01_Raw_Meta'!C12 -> Prospecting | E12: ='01_Raw_Meta'!D12 -> Creative_1 | F12: ='01_Raw_Meta'!E12 -> 65.26 | G12: ='01_Raw_Meta'!F12 -> 7966 | H12: ='01_Raw_Meta'!G12 -> 1058 | I12: ='01_Raw_Meta'!H12 -> 109 | J12: ='01_Raw_Meta'!I12 -> 19 | K12: ='01_Raw_Meta'!J12 -> 1078.95
A13: ='01_Raw_Meta'!A13 -> 46034 | B13: ="Meta" -> Meta | C13: ='01_Raw_Meta'!B13 -> Campaign_C | D13: ='01_Raw_Meta'!C13 -> Prospecting | E13: ='01_Raw_Meta'!D13 -> Creative_3 | F13: ='01_Raw_Meta'!E13 -> 271.6 | G13: ='01_Raw_Meta'!F13 -> 8079 | H13: ='01_Raw_Meta'!G13 -> 145 | I13: ='01_Raw_Meta'!H13 -> 53 | J13: ='01_Raw_Meta'!I13 -> 17 | K13: ='01_Raw_Meta'!J13 -> 1948.91
... A101: ='01_Raw_Meta'!A101 -> 46032 | B101: ="Meta" -> Meta | C101: ='01_Raw_Meta'!B101 -> Campaign_A | D101: ='01_Raw_Meta'!C101 -> Prospecting | E101: ='01_Raw_Meta'!D101 -> Creative_1 | F101: ='01_Raw_Meta'!E101 -> 30.46 | G101: ='01_Raw_Meta'!F101 -> 1412 | H101: ='01_Raw_Meta'!G101 -> 935 | I101: ='01_Raw_Meta'!H101 -> 99 | J101: ='01_Raw_Meta'!I101 -> 48 | K101: ='01_Raw_Meta'!J101 -> 1465.07

Sheet 11_Clean_Google
A1: Date | B1: Channel | C1: Campaign | D1: AdSet | E1: Ad | F1: Spend | G1: Impressions | H1: Clicks | I1: AddTocart | J1: Purchases | K1: Revenue
A2: ='02_Raw_Google'!A2 -> 46023 | B2: ="Google" -> Google | C2: ='02_Raw_Google'!B2 -> PMax | D2: ='02_Raw_Google'!C2 -> Group_2 | E2: ='02_Raw_Google'!D2 -> Headline_A | F2: ='02_Raw_Google'!E2 -> 74.66 | G2: ='02_Raw_Google'!F2 -> 6922 | H2: ='02_Raw_Google'!G2 -> 649 | I2: =0 -> 0 | J2: ='02_Raw_Google'!H2 -> 26 | K2: ='02_Raw_Google'!I2 -> 106.17
A3: ='02_Raw_Google'!A3 -> 46024 | B3: ="Google" -> Google | C3: ='02_Raw_Google'!B3 -> Search_Generic | D3: ='02_Raw_Google'!C3 -> Group_2 | E3: ='02_Raw_Google'!D3 -> Headline_C | F3: ='02_Raw_Google'!E3 -> 61.09 | G3: ='02_Raw_Google'!F3 -> 1281 | H3: ='02_Raw_Google'!G3 -> 217 | I3: =0 -> 0 | J3: ='02_Raw_Google'!H3 -> 3 | K3: ='02_Raw_Google'!I3 -> 693.78
A4: ='02_Raw_Google'!A4 -> 46025 | B4: ="Google" -> Google | C4: ='02_Raw_Google'!B4 -> PMax | D4: ='02_Raw_Google'!C4 -> Group_3 | E4: ='02_Raw_Google'!D4 -> Headline_A | F4: ='02_Raw_Google'!E4 -> 133.79 | G4: ='02_Raw_Google'!F4 -> 953 | H4: ='02_Raw_Google'!G4 -> 842 | I4: =0 -> 0 | J4: ='02_Raw_Google'!H4 -> 6 | K4: ='02_Raw_Google'!I4 -> 1272.97
A5: ='02_Raw_Google'!A5 -> 46026 | B5: ="Google" -> Google | C5: ='02_Raw_Google'!B5 -> Search_Brand | D5: ='02_Raw_Google'!C5 -> Group_3 | E5: ='02_Raw_Google'!D5 -> Headline_A | F5: ='02_Raw_Google'!E5 -> 154.84 | G5: ='02_Raw_Google'!F5 -> 8417 | H5: ='02_Raw_Google'!G5 -> 127 | I5: =0 -> 0 | J5: ='02_Raw_Google'!H5 -> 5 | K5: ='02_Raw_Google'!I5 -> 636.85
A6: ='02_Raw_Google'!A6 -> 46027 | B6: ="Google" -> Google | C6: ='02_Raw_Google'!B6 -> Search_Brand | D6: ='02_Raw_Google'!C6 -> Group_3 | E6: ='02_Raw_Google'!D6 -> Headline_A | F6: ='02_Raw_Google'!E6 -> 94.73 | G6: ='02_Raw_Google'!F6 -> 2324 | H6: ='02_Raw_Google'!G6 -> 160 | I6: =0 -> 0 | J6: ='02_Raw_Google'!H6 -> 5 | K6: ='02_Raw_Google'!I6 -> 334.89
A7: ='02_Raw_Google'!A7 -> 46028 | B7: ="Google" -> Google | C7: ='02_Raw_Google'!B7 -> Search_Generic | D7: ='02_Raw_Google'!C7 -> Group_2 | E7: ='02_Raw_Google'!D7 -> Headline_B | F7: ='02_Raw_Google'!E7 -> 148.82 | G7: ='02_Raw_Google'!F7 -> 2920 | H7: ='02_Raw_Google'!G7 -> 834 | I7: =0 -> 0 | J7: ='02_Raw_Google'!H7 -> 23 | K7: ='02_Raw_Google'!I7 -> 1150.25
A8: ='02_Raw_Google'!A8 -> 46029 | B8: ="Google" -> Google | C8: ='02_Raw_Google'!B8 -> Search_Generic | D8: ='02_Raw_Google'!C8 -> Group_3 | E8: ='02_Raw_Google'!D8 -> Headline_A | F8: ='02_Raw_Google'!E8 -> 223.55 | G8: ='02_Raw_Google'!F8 -> 3143 | H8: ='02_Raw_Google'!G8 -> 200 | I8: =0 -> 0 | J8: ='02_Raw_Google'!H8 -> 9 | K8: ='02_Raw_Google'!I8 -> 1200.11
A9: ='02_Raw_Google'!A9 -> 46030 | B9: ="Google" -> Google | C9: ='02_Raw_Google'!B9 -> Search_Generic | D9: ='02_Raw_Google'!C9 -> Group_3 | E9: ='02_Raw_Google'!D9 -> Headline_A | F9: ='02_Raw_Google'!E9 -> 145.83 | G9: ='02_Raw_Google'!F9 -> 5936 | H9: ='02_Raw_Google'!G9 -> 212 | I9: =0 -> 0 | J9: ='02_Raw_Google'!H9 -> 35 | K9: ='02_Raw_Google'!I9 -> 326.73
A10: ='02_Raw_Google'!A10 -> 46031 | B10: ="Google" -> Google | C10: ='02_Raw_Google'!B10 -> PMax | D10: ='02_Raw_Google'!C10 -> Group_1 | E10: ='02_Raw_Google'!D10 -> Headline_B | F10: ='02_Raw_Google'!E10 -> 184.39 | G10: ='02_Raw_Google'!F10 -> 6560 | H10: ='02_Raw_Google'!G10 -> 393 | I10: =0 -> 0 | J10: ='02_Raw_Google'!H10 -> 20 | K10: ='02_Raw_Google'!I10 -> 1174.61
A11: ='02_Raw_Google'!A11 -> 46032 | B11: ="Google" -> Google | C11: ='02_Raw_Google'!B11 -> Search_Brand | D11: ='02_Raw_Google'!C11 -> Group_1 | E11: ='02_Raw_Google'!D11 -> Headline_A | F11: ='02_Raw_Google'!E11 -> 204.25 | G11: ='02_Raw_Google'!F11 -> 2040 | H11: ='02_Raw_Google'!G11 -> 68 | I11: =0 -> 0 | J11: ='02_Raw_Google'!H11 -> 35 | K11: ='02_Raw_Google'!I11 -> 1425.16
A12: ='02_Raw_Google'!A12 -> 46033 | B12: ="Google" -> Google | C12: ='02_Raw_Google'!B12 -> Search_Brand | D12: ='02_Raw_Google'!C12 -> Group_2 | E12: ='02_Raw_Google'!D12 -> Headline_C | F12: ='02_Raw_Google'!E12 -> 247.35 | G12: ='02_Raw_Google'!F12 -> 860 | H12: ='02_Raw_Google'!G12 -> 556 | I12: =0 -> 0 | J12: ='02_Raw_Google'!H12 -> 18 | K12: ='02_Raw_Google'!I12 -> 316.26
A13: ='02_Raw_Google'!A13 -> 46034 | B13: ="Google" -> Google | C13: ='02_Raw_Google'!B13 -> PMax | D13: ='02_Raw_Google'!C13 -> Group_3 | E13: ='02_Raw_Google'!D13 -> Headline_C | F13: ='02_Raw_Google'!E13 -> 156.75 | G13: ='02_Raw_Google'!F13 -> 9930 | H13: ='02_Raw_Google'!G13 -> 526 | I13: =0 -> 0 | J13: ='02_Raw_Google'!H13 -> 17 | K13: ='02_Raw_Google'!I13 -> 1174.8
... A101: ='02_Raw_Google'!A101 -> 46032 | B101: ="Google" -> Google | C101: ='02_Raw_Google'!B101 -> PMax | D101: ='02_Raw_Google'!C101 -> Group_3 | E101: ='02_Raw_Google'!D101 -> Headline_C | F101: ='02_Raw_Google'!E101 -> 239.48 | G101: ='02_Raw_Google'!F101 -> 4023 | H101: ='02_Raw_Google'!G101 -> 255 | I101: =0 -> 0 | J101: ='02_Raw_Google'!H101 -> 30 | K101: ='02_Raw_Google'!I101 -> 890.68

Sheet 12_Clean_ShopifyData

Sheet 20_Model_Daily
A1: Date | B1: Channel | C1: Campaign | D1: AdSet | E1: Ad | F1: Spend | G1: Impressions | H1: Clicks | I1: AddToCart | J1: Purchases | K1: Revenue | L1: CTR | M1: CVR | N1: CPC | O1: CPA | P1: ROAS
A2: ='10_Clean_Meta'!A2 -> 46023 | B2: ='10_Clean_Meta'!B2 -> Meta | C2: ='10_Clean_Meta'!C2 -> Campaign_C | D2: ='10_Clean_Meta'!D2 -> Retargeting | E2: ='10_Clean_Meta'!E2 -> Creative_1 | F2: ='10_Clean_Meta'!F2 -> 272.12 | G2: ='10_Clean_Meta'!G2 -> 16338 | H2: ='10_Clean_Meta'!H2 -> 778 | ... K2: ='10_Clean_Meta'!K2 -> 748.97 | L2: =H2/G2 -> 0.047619048 | M2: =J2/H2 -> 0.0064267352 | N2: =F2/H2 -> 0.34976864 | O2: =F2/J2 -> 54.424 | P2: =K2/F2 -> 2.7523519
A3: ='10_Clean_Meta'!A3 -> 46024 | B3: ='10_Clean_Meta'!B3 -> Meta | C3: ='10_Clean_Meta'!C3 -> Campaign_A | D3: ='10_Clean_Meta'!D3 -> Retargeting | E3: ='10_Clean_Meta'!E3 -> Creative_3 | F3: ='10_Clean_Meta'!F3 -> 197.27 | G3: ='10_Clean_Meta'!G3 -> 3491 | H3: ='10_Clean_Meta'!H3 -> 1070 | ... K3: ='10_Clean_Meta'!K3 -> 1120.8 | L3: =H3/G3 -> 0.30650243 | M3: =J3/H3 -> 0.035514019 | N3: =F3/H3 -> 0.18436449 | O3: =F3/J3 -> 5.1913158 | P3: =K3/F3 -> 5.6815532
A4: ='10_Clean_Meta'!A4 -> 46025 | B4: ='10_Clean_Meta'!B4 -> Meta | C4: ='10_Clean_Meta'!C4 -> Campaign_C | D4: ='10_Clean_Meta'!D4 -> Retargeting | E4: ='10_Clean_Meta'!E4 -> Creative_2 | F4: ='10_Clean_Meta'!F4 -> 114.93 | G4: ='10_Clean_Meta'!G4 -> 16328 | H4: ='10_Clean_Meta'!H4 -> 810 | ... K4: ='10_Clean_Meta'!K4 -> 974.23 | L4: =H4/G4 -> 0.049608035 | M4: =J4/H4 -> 0.0037037037 | N4: =F4/H4 -> 0.14188889 | O4: =F4/J4 -> 38.31 | P4: =K4/F4 -> 8.476725
A5: ='10_Clean_Meta'!A5 -> 46026 | B5: ='10_Clean_Meta'!B5 -> Meta | C5: ='10_Clean_Meta'!C5 -> Campaign_C | D5: ='10_Clean_Meta'!D5 -> Prospecting | E5: ='10_Clean_Meta'!E5 -> Creative_1 | F5: ='10_Clean_Meta'!F5 -> 117.78 | G5: ='10_Clean_Meta'!G5 -> 15599 | H5: ='10_Clean_Meta'!H5 -> 725 | ... K5: ='10_Clean_Meta'!K5 -> 1211.06 | L5: =H5/G5 -> 0.046477338 | M5: =J5/H5 -> 0.073103448 | N5: =F5/H5 -> 0.16245517 | O5: =F5/J5 -> 2.2222642 | P5: =K5/F5 -> 10.282391
A6: ='10_Clean_Meta'!A6 -> 46027 | B6: ='10_Clean_Meta'!B6 -> Meta | C6: ='10_Clean_Meta'!C6 -> Campaign_A | D6: ='10_Clean_Meta'!D6 -> Prospecting | E6: ='10_Clean_Meta'!E6 -> Creative_1 | F6: ='10_Clean_Meta'!F6 -> 223.27 | G6: ='10_Clean_Meta'!G6 -> 4051 | H6: ='10_Clean_Meta'!H6 -> 506 | ... K6: ='10_Clean_Meta'!K6 -> 860.57 | L6: =H6/G6 -> 0.12490743 | M6: =J6/H6 -> 0.045454545 | N6: =F6/H6 -> 0.44124506 | O6: =F6/J6 -> 9.7073913 | P6: =K6/F6 -> 3.8543915
A7: ='10_Clean_Meta'!A7 -> 46028 | B7: ='10_Clean_Meta'!B7 -> Meta | C7: ='10_Clean_Meta'!C7 -> Campaign_A | D7: ='10_Clean_Meta'!D7 -> Prospecting | E7: ='10_Clean_Meta'!E7 -> Creative_1 | F7: ='10_Clean_Meta'!F7 -> 271.19 | G7: ='10_Clean_Meta'!G7 -> 16979 | H7: ='10_Clean_Meta'!H7 -> 969 | ... K7: ='10_Clean_Meta'!K7 -> 1425.57 | L7: =H7/G7 -> 0.057070499 | M7: =J7/H7 -> 0.038183695 | N7: =F7/H7 -> 0.27986584 | O7: =F7/J7 -> 7.3294595 | P7: =K7/F7 -> 5.2567204
A8: ='10_Clean_Meta'!A8 -> 46029 | B8: ='10_Clean_Meta'!B8 -> Meta | C8: ='10_Clean_Meta'!C8 -> Campaign_C | D8: ='10_Clean_Meta'!D8 -> Prospecting | E8: ='10_Clean_Meta'!E8 -> Creative_3 | F8: ='10_Clean_Meta'!F8 -> 268.38 | G8: ='10_Clean_Meta'!G8 -> 17388 | H8: ='10_Clean_Meta'!H8 -> 241 | ... K8: ='10_Clean_Meta'!K8 -> 442.13 | L8: =H8/G8 -> 0.013860133 | M8: =J8/H8 -> 0.21991701 | N8: =F8/H8 -> 1.11361 | O8: =F8/J8 -> 5.0637736 | P8: =K8/F8 -> 1.6474029
A9: ='10_Clean_Meta'!A9 -> 46030 | B9: ='10_Clean_Meta'!B9 -> Meta | C9: ='10_Clean_Meta'!C9 -> Campaign_B | D9: ='10_Clean_Meta'!D9 -> Retargeting | E9: ='10_Clean_Meta'!E9 -> Creative_2 | F9: ='10_Clean_Meta'!F9 -> 238.37 | G9: ='10_Clean_Meta'!G9 -> 1876 | H9: ='10_Clean_Meta'!H9 -> 788 | ... K9: ='10_Clean_Meta'!K9 -> 1423.35 | L9: =H9/G9 -> 0.42004264 | M9: =J9/H9 -> 0.046954315 | N9: =F9/H9 -> 0.3025 | O9: =F9/J9 -> 6.4424324 | P9: =K9/F9 -> 5.9711793
A10: ='10_Clean_Meta'!A10 -> 46031 | B10: ='10_Clean_Meta'!B10 -> Meta | C10: ='10_Clean_Meta'!C10 -> Campaign_C | D10: ='10_Clean_Meta'!D10 -> Prospecting | E10: ='10_Clean_Meta'!E10 -> Creative_1 | F10: ='10_Clean_Meta'!F10 -> 199.77 | G10: ='10_Clean_Meta'!G10 -> 5142 | H10: ='10_Clean_Meta'!H10 -> 1172 | ... K10: ='10_Clean_Meta'!K10 -> 882.16 | L10: =H10/G10 -> 0.22792688 | M10: =J10/H10 -> 0.0085324232 | N10: =F10/H10 -> 0.17045222 | O10: =F10/J10 -> 19.977 | P10: =K10/F10 -> 4.4158783
A11: ='10_Clean_Meta'!A11 -> 46032 | B11: ='10_Clean_Meta'!B11 -> Meta | C11: ='10_Clean_Meta'!C11 -> Campaign_C | D11: ='10_Clean_Meta'!D11 -> Prospecting | E11: ='10_Clean_Meta'!E11 -> Creative_1 | F11: ='10_Clean_Meta'!F11 -> 43.56 | G11: ='10_Clean_Meta'!G11 -> 16202 | H11: ='10_Clean_Meta'!H11 -> 1027 | ... K11: ='10_Clean_Meta'!K11 -> 1761.2 | L11: =H11/G11 -> 0.063387236 | M11: =J11/H11 -> 0.0097370983 | N11: =F11/H11 -> 0.0424148 | O11: =F11/J11 -> 4.356 | P11: =K11/F11 -> 40.431589
A12: ='10_Clean_Meta'!A12 -> 46033 | B12: ='10_Clean_Meta'!B12 -> Meta | C12: ='10_Clean_Meta'!C12 -> Campaign_C | D12: ='10_Clean_Meta'!D12 -> Prospecting | E12: ='10_Clean_Meta'!E12 -> Creative_1 | F12: ='10_Clean_Meta'!F12 -> 65.26 | G12: ='10_Clean_Meta'!G12 -> 7966 | H12: ='10_Clean_Meta'!H12 -> 1058 | ... K12: ='10_Clean_Meta'!K12 -> 1078.95 | L12: =H12/G12 -> 0.13281446 | M12: =J12/H12 -> 0.017958412 | N12: =F12/H12 -> 0.06168242 | O12: =F12/J12 -> 3.4347368 | P12: =K12/F12 -> 16.533098
A13: ='10_Clean_Meta'!A13 -> 46034 | B13: ='10_Clean_Meta'!B13 -> Meta | C13: ='10_Clean_Meta'!C13 -> Campaign_C | D13: ='10_Clean_Meta'!D13 -> Prospecting | E13: ='10_Clean_Meta'!E13 -> Creative_3 | F13: ='10_Clean_Meta'!F13 -> 271.6 | G13: ='10_Clean_Meta'!G13 -> 8079 | H13: ='10_Clean_Meta'!H13 -> 145 | ... K13: ='10_Clean_Meta'!K13 -> 1948.91 | L13: =H13/G13 -> 0.017947766 | M13: =J13/H13 -> 0.11724138 | N13: =F13/H13 -> 1.8731034 | O13: =F13/J13 -> 15.976471 | P13: =K13/F13 -> 7.1756627
... A101: ='10_Clean_Meta'!A101 -> 46032 | B101: ='10_Clean_Meta'!B101 -> Meta | C101: ='10_Clean_Meta'!C101 -> Campaign_A | D101: ='10_Clean_Meta'!D101 -> Prospecting | E101: ='10_Clean_Meta'!E101 -> Creative_1 | F101: ='10_Clean_Meta'!F101 -> 30.46 | G101: ='10_Clean_Meta'!G101 -> 1412 | H101: ='10_Clean_Meta'!H101 -> 935 | ... K101: ='10_Clean_Meta'!K101 -> 1465.07 | L101: =H101/G101 -> 0.6621813 | M101: =J101/H101 -> 0.051336898 | N101: =F101/H101 -> 0.03257754 | O101: =F101/J101 -> 0.63458333 | P101: =K101/F101 -> 48.098162
A102: ='11_Clean_Google'!A2 -> 46023 | B102: ='11_Clean_Google'!B2 -> Google | C102: ='11_Clean_Google'!C2 -> PMax | D102: ='11_Clean_Google'!D2 -> Group_2 | E102: ='11_Clean_Google'!E2 -> Headline_A | F102: ='11_Clean_Google'!F2 -> 74.66 | G102: ='11_Clean_Google'!G2 -> 6922 | H102: ='11_Clean_Google'!H2 -> 649 | ... K102: ='11_Clean_Google'!K2 -> 106.17 | L102: =H102/G102 -> 0.093759029 | M102: =J102/H102 -> 0.040061633 | N102: =F102/H102 -> 0.11503852 | O102: =F102/J102 -> 2.8715385 | P102: =K102/F102 -> 1.4220466
A103: ='11_Clean_Google'!A3 -> 46024 | B103: ='11_Clean_Google'!B3 -> Google | C103: ='11_Clean_Google'!C3 -> Search_Generic | D103: ='11_Clean_Google'!D3 -> Group_2 | E103: ='11_Clean_Google'!E3 -> Headline_C | F103: ='11_Clean_Google'!F3 -> 61.09 | G103: ='11_Clean_Google'!G3 -> 1281 | H103: ='11_Clean_Google'!H3 -> 217 | ... K103: ='11_Clean_Google'!K3 -> 693.78 | L103: =H103/G103 -> 0.16939891 | M103: =J103/H103 -> 0.013824885 | N103: =F103/H103 -> 0.28152074 | O103: =F103/J103 -> 20.363333 | P103: =K103/F103 -> 11.356687
A104: ='11_Clean_Google'!A4 -> 46025 | B104: ='11_Clean_Google'!B4 -> Google | C104: ='11_Clean_Google'!C4 -> PMax | D104: ='11_Clean_Google'!D4 -> Group_3 | E104: ='11_Clean_Google'!E4 -> Headline_A | F104: ='11_Clean_Google'!F4 -> 133.79 | G104: ='11_Clean_Google'!G4 -> 953 | H104: ='11_Clean_Google'!H4 -> 842 | ... K104: ='11_Clean_Google'!K4 -> 1272.97 | L104: =H104/G104 -> 0.88352571 | M104: =J104/H104 -> 0.0071258907 | N104: =F104/H104 -> 0.15889549 | O104: =F104/J104 -> 22.298333 | P104: =K104/F104 -> 9.5146872
A105: ='11_Clean_Google'!A5 -> 46026 | B105: ='11_Clean_Google'!B5 -> Google | C105: ='11_Clean_Google'!C5 -> Search_Brand | D105: ='11_Clean_Google'!D5 -> Group_3 | E105: ='11_Clean_Google'!E5 -> Headline_A | F105: ='11_Clean_Google'!F5 -> 154.84 | G105: ='11_Clean_Google'!G5 -> 8417 | H105: ='11_Clean_Google'!H5 -> 127 | ... K105: ='11_Clean_Google'!K5 -> 636.85 | L105: =H105/G105 -> 0.015088511 | M105: =J105/H105 -> 0.039370079 | N105: =F105/H105 -> 1.2192126 | O105: =F105/J105 -> 30.968 | P105: =K105/F105 -> 4.1129553
A106: ='11_Clean_Google'!A6 -> 46027 | B106: ='11_Clean_Google'!B6 -> Google | C106: ='11_Clean_Google'!C6 -> Search_Brand | D106: ='11_Clean_Google'!D6 -> Group_3 | E106: ='11_Clean_Google'!E6 -> Headline_A | F106: ='11_Clean_Google'!F6 -> 94.73 | G106: ='11_Clean_Google'!G6 -> 2324 | H106: ='11_Clean_Google'!H6 -> 160 | ... K106: ='11_Clean_Google'!K6 -> 334.89 | L106: =H106/G106 -> 0.068846816 | M106: =J106/H106 -> 0.03125 | N106: =F106/H106 -> 0.5920625 | O106: =F106/J106 -> 18.946 | P106: =K106/F106 -> 3.5352053
A107: ='11_Clean_Google'!A7 -> 46028 | B107: ='11_Clean_Google'!B7 -> Google | C107: ='11_Clean_Google'!C7 -> Search_Generic | D107: ='11_Clean_Google'!D7 -> Group_2 | E107: ='11_Clean_Google'!E7 -> Headline_B | F107: ='11_Clean_Google'!F7 -> 148.82 | G107: ='11_Clean_Google'!G7 -> 2920 | H107: ='11_Clean_Google'!H7 -> 834 | ... K107: ='11_Clean_Google'!K7 -> 1150.25 | L107: =H107/G107 -> 0.28561644 | M107: =J107/H107 -> 0.027577938 | N107: =F107/H107 -> 0.17844125 | O107: =F107/J107 -> 6.4704348 | P107: =K107/F107 -> 7.7291359
A108: ='11_Clean_Google'!A8 -> 46029 | B108: ='11_Clean_Google'!B8 -> Google | C108: ='11_Clean_Google'!C8 -> Search_Generic | D108: ='11_Clean_Google'!D8 -> Group_3 | E108: ='11_Clean_Google'!E8 -> Headline_A | F108: ='11_Clean_Google'!F8 -> 223.55 | G108: ='11_Clean_Google'!G8 -> 3143 | H108: ='11_Clean_Google'!H8 -> 200 | ... K108: ='11_Clean_Google'!K8 -> 1200.11 | L108: =H108/G108 -> 0.063633471 | M108: =J108/H108 -> 0.045 | N108: =F108/H108 -> 1.11775 | O108: =F108/J108 -> 24.838889 | P108: =K108/F108 -> 5.3684187
A109: ='11_Clean_Google'!A9 -> 46030 | B109: ='11_Clean_Google'!B9 -> Google | C109: ='11_Clean_Google'!C9 -> Search_Generic | D109: ='11_Clean_Google'!D9 -> Group_3 | E109: ='11_Clean_Google'!E9 -> Headline_A | F109: ='11_Clean_Google'!F9 -> 145.83 | G109: ='11_Clean_Google'!G9 -> 5936 | H109: ='11_Clean_Google'!H9 -> 212 | ... K109: ='11_Clean_Google'!K9 -> 326.73 | L109: =H109/G109 -> 0.035714286 | M109: =J109/H109 -> 0.16509434 | N109: =F109/H109 -> 0.68787736 | O109: =F109/J109 -> 4.1665714 | P109: =K109/F109 -> 2.2404855
A110: ='11_Clean_Google'!A10 -> 46031 | B110: ='11_Clean_Google'!B10 -> Google | C110: ='11_Clean_Google'!C10 -> PMax | D110: ='11_Clean_Google'!D10 -> Group_1 | E110: ='11_Clean_Google'!E10 -> Headline_B | F110: ='11_Clean_Google'!F10 -> 184.39 | G110: ='11_Clean_Google'!G10 -> 6560 | H110: ='11_Clean_Google'!H10 -> 393 | ... K110: ='11_Clean_Google'!K10 -> 1174.61 | L110: =H110/G110 -> 0.059908537 | M110: =J110/H110 -> 0.050890585 | N110: =F110/H110 -> 0.46918575 | O110: =F110/J110 -> 9.2195 | P110: =K110/F110 -> 6.3702478
A111: ='11_Clean_Google'!A11 -> 46032 | B111: ='11_Clean_Google'!B11 -> Google | C111: ='11_Clean_Google'!C11 -> Search_Brand | D111: ='11_Clean_Google'!D11 -> Group_1 | E111: ='11_Clean_Google'!E11 -> Headline_A | F111: ='11_Clean_Google'!F11 -> 204.25 | G111: ='11_Clean_Google'!G11 -> 2040 | H111: ='11_Clean_Google'!H11 -> 68 | ... K111: ='11_Clean_Google'!K11 -> 1425.16 | L111: =H111/G111 -> 0.033333333 | M111: =J111/H111 -> 0.51470588 | N111: =F111/H111 -> 3.0036765 | O111: =F111/J111 -> 5.8357143 | P111: =K111/F111 -> 6.9775275
A112: ='11_Clean_Google'!A12 -> 46033 | B112: ='11_Clean_Google'!B12 -> Google | C112: ='11_Clean_Google'!C12 -> Search_Brand | D112: ='11_Clean_Google'!D12 -> Group_2 | E112: ='11_Clean_Google'!E12 -> Headline_C | F112: ='11_Clean_Google'!F12 -> 247.35 | G112: ='11_Clean_Google'!G12 -> 860 | H112: ='11_Clean_Google'!H12 -> 556 | ... K112: ='11_Clean_Google'!K12 -> 316.26 | L112: =H112/G112 -> 0.64651163 | M112: =J112/H112 -> 0.032374101 | N112: =F112/H112 -> 0.4448741 | O112: =F112/J112 -> 13.741667 | P112: =K112/F112 -> 1.2785931
A113: ='11_Clean_Google'!A13 -> 46034 | B113: ='11_Clean_Google'!B13 -> Google | C113: ='11_Clean_Google'!C13 -> PMax | D113: ='11_Clean_Google'!D13 -> Group_3 | E113: ='11_Clean_Google'!E13 -> Headline_C | F113: ='11_Clean_Google'!F13 -> 156.75 | G113: ='11_Clean_Google'!G13 -> 9930 | H113: ='11_Clean_Google'!H13 -> 526 | ... K113: ='11_Clean_Google'!K13 -> 1174.8 | L113: =H113/G113 -> 0.052970796 | M113: =J113/H113 -> 0.032319392 | N113: =F113/H113 -> 0.2980038 | O113: =F113/J113 -> 9.2205882 | P113: =K113/F113 -> 7.4947368
... A201: ='11_Clean_Google'!A101 -> 46032 | B201: ='11_Clean_Google'!B101 -> Google | C201: ='11_Clean_Google'!C101 -> PMax | D201: ='11_Clean_Google'!D101 -> Group_3 | E201: ='11_Clean_Google'!E101 -> Headline_C | F201: ='11_Clean_Google'!F101 -> 239.48 | G201: ='11_Clean_Google'!G101 -> 4023 | H201: ='11_Clean_Google'!H101 -> 255 | ... K201: ='11_Clean_Google'!K101 -> 890.68 | L201: =H201/G201 -> 0.063385533 | M201: =J201/H201 -> 0.11764706 | N201: =F201/H201 -> 0.93913725 | O201: =F201/J201 -> 7.9826667 | P201: =K201/F201 -> 3.719225

Sheet 21_Model_Filtered
A1: Date | B1: Channel | C1: Campaign | D1: AdSet | E1: Ad | F1: Spend | G1: Impressions | H1: Clicks | I1: AddToCart | J1: Purchases | K1: Revenue | L1: CTR | M1: CVR | N1: CPC | O1: CPA | P1: ROAS
A2: {=_xlfn._xlws.FILTER('20_Model_Daily'!A2:P1000, ('20_Model_Daily'!A2:A1000>='00_Control'!B3)* ('20_Model_Daily'!A2:A1000<='00_Control'!B4))} -> 46037 | B2: Meta | C2: Campaign_B | D2: Prospecting | E2: Creative_3 | F2: 48.41 | G2: 5465 | H2: 328 | I2: 35 | J2: 9 | K2: 1661.4 | L2: 0.060018298 | M2: 0.027439024 | N2: 0.14759146 | O2: 5.3788889 | P2: 34.319356
A3: 46038 | B3: Meta | C3: Campaign_A | D3: Retargeting | E3: Creative_1 | F3: 205.78 | G3: 18019 | H3: 266 | I3: 5 | J3: 46 | K3: 755.66 | L3: 0.014762195 | M3: 0.17293233 | N3: 0.77360902 | O3: 4.4734783 | P3: 3.6721742
A4: 46039 | B4: Meta | C4: Campaign_B | D4: Prospecting | E4: Creative_2 | F4: 21.42 | G4: 14417 | H4: 916 | I4: 58 | J4: 1 | K4: 760.48 | L4: 0.063536103 | M4: 0.0010917031 | N4: 0.023384279 | O4: 21.42 | P4: 35.503268
A5: 46040 | B5: Meta | C5: Campaign_B | D5: Retargeting | E5: Creative_1 | F5: 65.03 | G5: 19077 | H5: 922 | I5: 7 | J5: 51 | K5: 160.43 | L5: 0.04833045 | M5: 0.055314534 | N5: 0.070531453 | O5: 1.275098 | P5: 2.4670152
A6: 46041 | B6: Meta | C6: Campaign_B | D6: Prospecting | E6: Creative_1 | F6: 173.65 | G6: 9311 | H6: 111 | I6: 20 | J6: 45 | K6: 1142.56 | L6: 0.011921383 | M6: 0.40540541 | N6: 1.5644144 | O6: 3.8588889 | P6: 6.5796718
A7: 46042 | B7: Meta | C7: Campaign_B | D7: Prospecting | E7: Creative_3 | F7: 213.73 | G7: 18214 | H7: 645 | I7: 91 | J7: 13 | K7: 1115.4 | L7: 0.03541232 | M7: 0.020155039 | N7: 0.33136434 | O7: 16.440769 | P7: 5.2187339
A8: 46043 | B8: Meta | C8: Campaign_A | D8: Retargeting | E8: Creative_2 | F8: 202.55 | G8: 15098 | H8: 778 | I8: 61 | J8: 4 | K8: 776.38 | L8: 0.051530004 | M8: 0.0051413882 | N8: 0.26034704 | O8: 50.6375 | P8: 3.8330289
A9: 46044 | B9: Meta | C9: Campaign_A | D9: Retargeting | E9: Creative_3 | F9: 82.8 | G9: 6177 | H9: 446 | I9: 79 | J9: 1 | K9: 1799.01 | L9: 0.072203335 | M9: 0.0022421525 | N9: 0.18565022 | O9: 82.8 | P9: 21.727174
A10: 46045 | B10: Meta | C10: Campaign_B | D10: Retargeting | E10: Creative_3 | F10: 219.41 | G10: 15262 | H10: 748 | I10: 16 | J10: 49 | K10: 344.62 | L10: 0.049010615 | M10: 0.065508021 | N10: 0.29332888 | O10: 4.4777551 | P10: 1.5706668
A11: 46046 | B11: Meta | C11: Campaign_B | D11: Prospecting | E11: Creative_2 | F11: 86.43 | G11: 9308 | H11: 1092 | I11: 78 | J11: 40 | K11: 727.19 | L11: 0.11731844 | M11: 0.036630037 | N11: 0.079148352 | O11: 2.16075 | P11: 8.4136295
A12: 46047 | B12: Meta | C12: Campaign_A | D12: Retargeting | E12: Creative_1 | F12: 111.11 | G12: 6949 | H12: 226 | I12: 100 | J12: 32 | K12: 711.01 | L12: 0.032522665 | M12: 0.14159292 | N12: 0.49163717 | O12: 3.4721875 | P12: 6.399154
A13: 46048 | B13: Meta | C13: Campaign_A | D13: Prospecting | E13: Creative_1 | F13: 229.02 | G13: 2150 | H13: 445 | I13: 20 | J13: 34 | K13: 275.35 | L13: 0.20697674 | M13: 0.076404494 | N13: 0.51465169 | O13: 6.7358824 | P13: 1.2022967
A14: 46049 | B14: Meta | C14: Campaign_A | D14: Prospecting | E14: Creative_2 | F14: 201.9 | G14: 2931 | H14: 494 | I14: 76 | J14: 28 | K14: 1014.18 | L14: 0.16854316 | M14: 0.056680162 | N14: 0.40870445 | O14: 7.2107143 | P14: 5.0231798
... A97: 46052 | B97: Google | C97: Search_Brand | D97: Group_2 | E97: Headline_B | F97: 238.09 | G97: 3219 | H97: 613 | I97: 0 | J97: 32 | K97: 1464.07 | L97: 0.19043181 | M97: 0.052202284 | N97: 0.38840131 | O97: 7.4403125 | P97: 6.1492293

Sheet 30_Campaign_Perf
A1: Campaign | B1: Spend | C1: Purchases | D1: Revenue | E1: ROAS | F1: CPA | G1: CVR | H1: Decision
A2: {=_xlfn.UNIQUE('21_Model_Filtered'!C2:C10000)} -> Campaign_B | B2: =SUMIFS('21_Model_Filtered'!F:F,'21_Model_Filtered'!C:C,A2) -> 3473.34 | C2: =SUMIFS('21_Model_Filtered'!J:J,'21_Model_Filtered'!C:C,A2) -> 656 | D2: =SUMIFS('21_Model_Filtered'!K:K,'21_Model_Filtered'!C:C,A2) -> 15964.28 | E2: =IFERROR(D2/B2,0) -> 4.596233 | F2: =IFERROR(B2/C2,0) -> 5.2947256 | G2: =IFERROR(C2/SUMIFS('21_Model_Filtered'!H:H,'21_Model_Filtered'!C:C,A2),0) -> 0.04813619 | H2: =IF(AND(B2>='00_Control'!B6,C2>='00_Control'!B7,E2>='00_Control'!B8),"SCALE", IF(E2<='00_Control'!B9,"KILL","WATCH")) -> SCALE
A3: Campaign_A | B3: =SUMIFS('21_Model_Filtered'!F:F,'21_Model_Filtered'!C:C,A3) -> 2900.89 | C3: =SUMIFS('21_Model_Filtered'!J:J,'21_Model_Filtered'!C:C,A3) -> 328 | D3: =SUMIFS('21_Model_Filtered'!K:K,'21_Model_Filtered'!C:C,A3) -> 14381.26 | E3: =IFERROR(D3/B3,0) -> 4.9575337 | F3: =IFERROR(B3/C3,0) -> 8.8441768 | G3: =IFERROR(C3/SUMIFS('21_Model_Filtered'!H:H,'21_Model_Filtered'!C:C,A3),0) -> 0.02924133 | H3: =IF(AND(B3>='00_Control'!B7,C3>='00_Control'!B8,E3>='00_Control'!B9),"SCALE", IF(E3<='00_Control'!B10,"KILL","WATCH")) -> SCALE
A4: Campaign_C | B4: =SUMIFS('21_Model_Filtered'!F:F,'21_Model_Filtered'!C:C,A4) -> 2306.76 | C4: =SUMIFS('21_Model_Filtered'!J:J,'21_Model_Filtered'!C:C,A4) -> 358 | D4: =SUMIFS('21_Model_Filtered'!K:K,'21_Model_Filtered'!C:C,A4) -> 13294.85 | E4: =IFERROR(D4/B4,0) -> 5.7634301 | F4: =IFERROR(B4/C4,0) -> 6.4434637 | G4: =IFERROR(C4/SUMIFS('21_Model_Filtered'!H:H,'21_Model_Filtered'!C:C,A4),0) -> 0.048621486 | H4: =IF(AND(B4>='00_Control'!B8,C4>='00_Control'!B9,E4>='00_Control'!B10),"SCALE", IF(E4<='00_Control'!B11,"KILL","WATCH")) -> SCALE
A5: Search_Generic | B5: =SUMIFS('21_Model_Filtered'!F:F,'21_Model_Filtered'!C:C,A5) -> 2323.31 | C5: =SUMIFS('21_Model_Filtered'!J:J,'21_Model_Filtered'!C:C,A5) -> 342 | D5: =SUMIFS('21_Model_Filtered'!K:K,'21_Model_Filtered'!C:C,A5) -> 12392.25 | E5: =IFERROR(D5/B5,0) -> 5.3338771 | F5: =IFERROR(B5/C5,0) -> 6.7933041 | G5: =IFERROR(C5/SUMIFS('21_Model_Filtered'!H:H,'21_Model_Filtered'!C:C,A5),0) -> 0.051849606 | H5: =IF(AND(B5>='00_Control'!B9,C5>='00_Control'!B10,E5>='00_Control'!B11),"SCALE", IF(E5<='00_Control'!B12,"KILL","WATCH")) -> KILL
A6: Search_Brand | B6: =SUMIFS('21_Model_Filtered'!F:F,'21_Model_Filtered'!C:C,A6) -> 2874.07 | C6: =SUMIFS('21_Model_Filtered'!J:J,'21_Model_Filtered'!C:C,A6) -> 365 | D6: =SUMIFS('21_Model_Filtered'!K:K,'21_Model_Filtered'!C:C,A6) -> 16300.48 | E6: =IFERROR(D6/B6,0) -> 5.6715668 | F6: =IFERROR(B6/C6,0) -> 7.8741644 | G6: =IFERROR(C6/SUMIFS('21_Model_Filtered'!H:H,'21_Model_Filtered'!C:C,A6),0) -> 0.044867855 | H6: =IF(AND(B6>='00_Control'!B10,C6>='00_Control'!B11,E6>='00_Control'!B12),"SCALE", IF(E6<='00_Control'!B13,"KILL","WATCH")) -> WATCH
A7: PMax | B7: =SUMIFS('21_Model_Filtered'!F:F,'21_Model_Filtered'!C:C,A7) -> 1956.3 | C7: =SUMIFS('21_Model_Filtered'!J:J,'21_Model_Filtered'!C:C,A7) -> 313 | D7: =SUMIFS('21_Model_Filtered'!K:K,'21_Model_Filtered'!C:C,A7) -> 11201.16 | E7: =IFERROR(D7/B7,0) -> 5.7256862 | F7: =IFERROR(B7/C7,0) -> 6.2501597 | G7: =IFERROR(C7/SUMIFS('21_Model_Filtered'!H:H,'21_Model_Filtered'!C:C,A7),0) -> 0.043508479 | H7: =IF(AND(B7>='00_Control'!B11,C7>='00_Control'!B12,E7>='00_Control'!B13),"SCALE", IF(E7<='00_Control'!B14,"KILL","WATCH")) -> SCALE
A8: 0 | B8: =SUMIFS('21_Model_Filtered'!F:F,'21_Model_Filtered'!C:C,A8) -> 0 | C8: =SUMIFS('21_Model_Filtered'!J:J,'21_Model_Filtered'!C:C,A8) -> 0 | D8: =SUMIFS('21_Model_Filtered'!K:K,'21_Model_Filtered'!C:C,A8) -> 0 | E8: =IFERROR(D8/B8,0) -> 0 | F8: =IFERROR(B8/C8,0) -> 0 | G8: =IFERROR(C8/SUMIFS('21_Model_Filtered'!H:H,'21_Model_Filtered'!C:C,A8),0) -> 0 | H8: =IF(AND(B8>='00_Control'!B12,C8>='00_Control'!B13,E8>='00_Control'!B14),"SCALE", IF(E8<='00_Control'!B15,"KILL","WATCH")) -> KILL

Sheet 31_Creative_Perf
A1: Campaign | B1: Ad | C1: Spend | D1: Purchases | E1: Revenue | F1: ROAS | G1: CPA | H1: CTR | I1: Decision
A2: {=_xlfn.UNIQUE(_xlfn._xlws.FILTER(CHOOSE({1,2},'21_Model_Filtered'!C2:C10000,'21_Model_Filtered'!E2:E10000),'21_Model_Filtered'!E2:E10000<>""))} -> Campaign_B | B2: Creative_3 | C2: =SUMIFS('21_Model_Filtered'!F:F,'21_Model_Filtered'!C:C,$A2,'21_Model_Filtered'!E:E,$B2) -> 1668.22 | D2: =SUMIFS('21_Model_Filtered'!J:J,'21_Model_Filtered'!C:C,$A2,'21_Model_Filtered'!E:E,$B2) -> 265 | E2: =SUMIFS('21_Model_Filtered'!K:K,'21_Model_Filtered'!C:C,$A2,'21_Model_Filtered'!E:E,$B2) -> 8044.71 | F2: =IFERROR(E2/C2,0) -> 4.8223316 | G2: =IFERROR(C2/D2,0) -> 6.2951698 | H2: =IFERROR( SUMIFS('21_Model_Filtered'!H:H,'21_Model_Filtered'!C:C,$A2,'21_Model_Filtered'!E:E,$B2) / SUMIFS('21_Model_Filtered'!G:G,'21_Model_Filtered'!C:C,$A2,'21_Model_Filtered'!E:E,$B2),0) -> 0.072008954 | I2: =IF(AND(C2>='00_Control'!B6,D2>='00_Control'!B7,F2>='00_Control'!B8),"SCALE", IF(F2<='00_Control'!B9,"KILL","WATCH")) -> SCALE
A3: Campaign_A | B3: Creative_1 | C3: =SUMIFS('21_Model_Filtered'!F:F,'21_Model_Filtered'!C:C,$A3,'21_Model_Filtered'!E:E,$B3) -> 888.05 | D3: =SUMIFS('21_Model_Filtered'!J:J,'21_Model_Filtered'!C:C,$A3,'21_Model_Filtered'!E:E,$B3) -> 152 | E3: =SUMIFS('21_Model_Filtered'!K:K,'21_Model_Filtered'!C:C,$A3,'21_Model_Filtered'!E:E,$B3) -> 3726.08 | F3: =IFERROR(E3/C3,0) -> 4.1957998 | G3: =IFERROR(C3/D3,0) -> 5.8424342 | H3: =IFERROR( SUMIFS('21_Model_Filtered'!H:H,'21_Model_Filtered'!C:C,$A3,'21_Model_Filtered'!E:E,$B3) / SUMIFS('21_Model_Filtered'!G:G,'21_Model_Filtered'!C:C,$A3,'21_Model_Filtered'!E:E,$B3),0) -> 0.060048753 | I3: =IF(AND(C3>='00_Control'!B7,D3>='00_Control'!B8,F3>='00_Control'!B9),"SCALE", IF(F3<='00_Control'!B10,"KILL","WATCH")) -> SCALE
A4: Campaign_B | B4: Creative_2 | C4: =SUMIFS('21_Model_Filtered'!F:F,'21_Model_Filtered'!C:C,$A4,'21_Model_Filtered'!E:E,$B4) -> 667.34 | D4: =SUMIFS('21_Model_Filtered'!J:J,'21_Model_Filtered'!C:C,$A4,'21_Model_Filtered'!E:E,$B4) -> 112 | E4: =SUMIFS('21_Model_Filtered'!K:K,'21_Model_Filtered'!C:C,$A4,'21_Model_Filtered'!E:E,$B4) -> 2418.45 | F4: =IFERROR(E4/C4,0) -> 3.6240147 | G4: =IFERROR(C4/D4,0) -> 5.9583929 | H4: =IFERROR( SUMIFS('21_Model_Filtered'!H:H,'21_Model_Filtered'!C:C,$A4,'21_Model_Filtered'!E:E,$B4) / SUMIFS('21_Model_Filtered'!G:G,'21_Model_Filtered'!C:C,$A4,'21_Model_Filtered'!E:E,$B4),0) -> 0.072168565 | I4: =IF(AND(C4>='00_Control'!B8,D4>='00_Control'!B9,F4>='00_Control'!B10),"SCALE", IF(F4<='00_Control'!B11,"KILL","WATCH")) -> SCALE
A5: Campaign_B | B5: Creative_1 | C5: =SUMIFS('21_Model_Filtered'!F:F,'21_Model_Filtered'!C:C,$A5,'21_Model_Filtered'!E:E,$B5) -> 1137.78 | D5: =SUMIFS('21_Model_Filtered'!J:J,'21_Model_Filtered'!C:C,$A5,'21_Model_Filtered'!E:E,$B5) -> 279 | E5: =SUMIFS('21_Model_Filtered'!K:K,'21_Model_Filtered'!C:C,$A5,'21_Model_Filtered'!E:E,$B5) -> 5501.12 | F5: =IFERROR(E5/C5,0) -> 4.8349593 | G5: =IFERROR(C5/D5,0) -> 4.0780645 | H5: =IFERROR( SUMIFS('21_Model_Filtered'!H:H,'21_Model_Filtered'!C:C,$A5,'21_Model_Filtered'!E:E,$B5) / SUMIFS('21_Model_Filtered'!G:G,'21_Model_Filtered'!C:C,$A5,'21_Model_Filtered'!E:E,$B5),0) -> 0.051891945 | I5: =IF(AND(C5>='00_Control'!B9,D5>='00_Control'!B10,F5>='00_Control'!B11),"SCALE", IF(F5<='00_Control'!B12,"KILL","WATCH")) -> KILL
A6: Campaign_A | B6: Creative_2 | C6: =SUMIFS('21_Model_Filtered'!F:F,'21_Model_Filtered'!C:C,$A6,'21_Model_Filtered'!E:E,$B6) -> 988.03 | D6: =SUMIFS('21_Model_Filtered'!J:J,'21_Model_Filtered'!C:C,$A6,'21_Model_Filtered'!E:E,$B6) -> 89 | E6: =SUMIFS('21_Model_Filtered'!K:K,'21_Model_Filtered'!C:C,$A6,'21_Model_Filtered'!E:E,$B6) -> 6620.51 | F6: =IFERROR(E6/C6,0) -> 6.7007176 | G6: =IFERROR(C6/D6,0) -> 11.101461 | H6: =IFERROR( SUMIFS('21_Model_Filtered'!H:H,'21_Model_Filtered'!C:C,$A6,'21_Model_Filtered'!E:E,$B6) / SUMIFS('21_Model_Filtered'!G:G,'21_Model_Filtered'!C:C,$A6,'21_Model_Filtered'!E:E,$B6),0) -> 0.059445383 | I6: =IF(AND(C6>='00_Control'!B10,D6>='00_Control'!B11,F6>='00_Control'!B12),"SCALE", IF(F6<='00_Control'!B13,"KILL","WATCH")) -> WATCH
A7: Campaign_A | B7: Creative_3 | C7: =SUMIFS('21_Model_Filtered'!F:F,'21_Model_Filtered'!C:C,$A7,'21_Model_Filtered'!E:E,$B7) -> 1024.81 | D7: =SUMIFS('21_Model_Filtered'!J:J,'21_Model_Filtered'!C:C,$A7,'21_Model_Filtered'!E:E,$B7) -> 87 | E7: =SUMIFS('21_Model_Filtered'!K:K,'21_Model_Filtered'!C:C,$A7,'21_Model_Filtered'!E:E,$B7) -> 4034.67 | F7: =IFERROR(E7/C7,0) -> 3.9369932 | G7: =IFERROR(C7/D7,0) -> 11.779425 | H7: =IFERROR( SUMIFS('21_Model_Filtered'!H:H,'21_Model_Filtered'!C:C,$A7,'21_Model_Filtered'!E:E,$B7) / SUMIFS('21_Model_Filtered'!G:G,'21_Model_Filtered'!C:C,$A7,'21_Model_Filtered'!E:E,$B7),0) -> 0.072474481 | I7: =IF(AND(C7>='00_Control'!B11,D7>='00_Control'!B12,F7>='00_Control'!B13),"SCALE", IF(F7<='00_Control'!B14,"KILL","WATCH")) -> SCALE
A8: Campaign_C | B8: Creative_1 | C8: =SUMIFS('21_Model_Filtered'!F:F,'21_Model_Filtered'!C:C,$A8,'21_Model_Filtered'!E:E,$B8) -> 948.85 | D8: =SUMIFS('21_Model_Filtered'!J:J,'21_Model_Filtered'!C:C,$A8,'21_Model_Filtered'!E:E,$B8) -> 181 | E8: =SUMIFS('21_Model_Filtered'!K:K,'21_Model_Filtered'!C:C,$A8,'21_Model_Filtered'!E:E,$B8) -> 5167.18 | F8: =IFERROR(E8/C8,0) -> 5.445729 | G8: =IFERROR(C8/D8,0) -> 5.2422652 | H8: =IFERROR( SUMIFS('21_Model_Filtered'!H:H,'21_Model_Filtered'!C:C,$A8,'21_Model_Filtered'!E:E,$B8) / SUMIFS('21_Model_Filtered'!G:G,'21_Model_Filtered'!C:C,$A8,'21_Model_Filtered'!E:E,$B8),0) -> 0.1242187 | I8: =IF(AND(C8>='00_Control'!B12,D8>='00_Control'!B13,F8>='00_Control'!B14),"SCALE", IF(F8<='00_Control'!B15,"KILL","WATCH")) -> SCALE
A9: Campaign_C | B9: Creative_2 | C9: =SUMIFS('21_Model_Filtered'!F:F,'21_Model_Filtered'!C:C,$A9,'21_Model_Filtered'!E:E,$B9) -> 702.26 | D9: =SUMIFS('21_Model_Filtered'!J:J,'21_Model_Filtered'!C:C,$A9,'21_Model_Filtered'!E:E,$B9) -> 103 | E9: =SUMIFS('21_Model_Filtered'!K:K,'21_Model_Filtered'!C:C,$A9,'21_Model_Filtered'!E:E,$B9) -> 4287.95 | F9: =IFERROR(E9/C9,0) -> 6.1059294 | G9: =IFERROR(C9/D9,0) -> 6.8180583 | H9: =IFERROR( SUMIFS('21_Model_Filtered'!H:H,'21_Model_Filtered'!C:C,$A9,'21_Model_Filtered'!E:E,$B9) / SUMIFS('21_Model_Filtered'!G:G,'21_Model_Filtered'!C:C,$A9,'21_Model_Filtered'!E:E,$B9),0) -> 0.031451036 | I9: =IF(AND(C9>='00_Control'!B13,D9>='00_Control'!B14,F9>='00_Control'!B15),"SCALE", IF(F9<='00_Control'!B16,"KILL","WATCH")) -> SCALE
A10: Campaign_C | B10: Creative_3 | C10: =SUMIFS('21_Model_Filtered'!F:F,'21_Model_Filtered'!C:C,$A10,'21_Model_Filtered'!E:E,$B10) -> 655.65 | D10: =SUMIFS('21_Model_Filtered'!J:J,'21_Model_Filtered'!C:C,$A10,'21_Model_Filtered'!E:E,$B10) -> 74 | E10: =SUMIFS('21_Model_Filtered'!K:K,'21_Model_Filtered'!C:C,$A10,'21_Model_Filtered'!E:E,$B10) -> 3839.72 | F10: =IFERROR(E10/C10,0) -> 5.8563563 | G10: =IFERROR(C10/D10,0) -> 8.8601351 | H10: =IFERROR( SUMIFS('21_Model_Filtered'!H:H,'21_Model_Filtered'!C:C,$A10,'21_Model_Filtered'!E:E,$B10) / SUMIFS('21_Model_Filtered'!G:G,'21_Model_Filtered'!C:C,$A10,'21_Model_Filtered'!E:E,$B10),0) -> 0.16803606 | I10: =IF(AND(C10>='00_Control'!B14,D10>='00_Control'!B15,F10>='00_Control'!B16),"SCALE", IF(F10<='00_Control'!B17,"KILL","WATCH")) -> SCALE
A11: Search_Generic | B11: Headline_C | C11: =SUMIFS('21_Model_Filtered'!F:F,'21_Model_Filtered'!C:C,$A11,'21_Model_Filtered'!E:E,$B11) -> 1520.57 | D11: =SUMIFS('21_Model_Filtered'!J:J,'21_Model_Filtered'!C:C,$A11,'21_Model_Filtered'!E:E,$B11) -> 148 | E11: =SUMIFS('21_Model_Filtered'!K:K,'21_Model_Filtered'!C:C,$A11,'21_Model_Filtered'!E:E,$B11) -> 8660.46 | F11: =IFERROR(E11/C11,0) -> 5.6955352 | G11: =IFERROR(C11/D11,0) -> 10.274122 | H11: =IFERROR( SUMIFS('21_Model_Filtered'!H:H,'21_Model_Filtered'!C:C,$A11,'21_Model_Filtered'!E:E,$B11) / SUMIFS('21_Model_Filtered'!G:G,'21_Model_Filtered'!C:C,$A11,'21_Model_Filtered'!E:E,$B11),0) -> 0.039598887 | I11: =IF(AND(C11>='00_Control'!B15,D11>='00_Control'!B16,F11>='00_Control'!B17),"SCALE", IF(F11<='00_Control'!B18,"KILL","WATCH")) -> SCALE
A12: Search_Generic | B12: Headline_B | C12: =SUMIFS('21_Model_Filtered'!F:F,'21_Model_Filtered'!C:C,$A12,'21_Model_Filtered'!E:E,$B12) -> 569.1 | D12: =SUMIFS('21_Model_Filtered'!J:J,'21_Model_Filtered'!C:C,$A12,'21_Model_Filtered'!E:E,$B12) -> 135 | E12: =SUMIFS('21_Model_Filtered'!K:K,'21_Model_Filtered'!C:C,$A12,'21_Model_Filtered'!E:E,$B12) -> 1382.36 | F12: =IFERROR(E12/C12,0) -> 2.4290283 | G12: =IFERROR(C12/D12,0) -> 4.2155556 | H12: =IFERROR( SUMIFS('21_Model_Filtered'!H:H,'21_Model_Filtered'!C:C,$A12,'21_Model_Filtered'!E:E,$B12) / SUMIFS('21_Model_Filtered'!G:G,'21_Model_Filtered'!C:C,$A12,'21_Model_Filtered'!E:E,$B12),0) -> 0.044875974 | I12: =IF(AND(C12>='00_Control'!B16,D12>='00_Control'!B17,F12>='00_Control'!B18),"SCALE", IF(F12<='00_Control'!B19,"KILL","WATCH")) -> SCALE
A13: Search_Brand | B13: Headline_B | C13: =SUMIFS('21_Model_Filtered'!F:F,'21_Model_Filtered'!C:C,$A13,'21_Model_Filtered'!E:E,$B13) -> 1555.76 | D13: =SUMIFS('21_Model_Filtered'!J:J,'21_Model_Filtered'!C:C,$A13,'21_Model_Filtered'!E:E,$B13) -> 232 | E13: =SUMIFS('21_Model_Filtered'!K:K,'21_Model_Filtered'!C:C,$A13,'21_Model_Filtered'!E:E,$B13) -> 9593.64 | F13: =IFERROR(E13/C13,0) -> 6.1665295 | G13: =IFERROR(C13/D13,0) -> 6.7058621 | H13: =IFERROR( SUMIFS('21_Model_Filtered'!H:H,'21_Model_Filtered'!C:C,$A13,'21_Model_Filtered'!E:E,$B13) / SUMIFS('21_Model_Filtered'!G:G,'21_Model_Filtered'!C:C,$A13,'21_Model_Filtered'!E:E,$B13),0) -> 0.064902957 | I13: =IF(AND(C13>='00_Control'!B17,D13>='00_Control'!B18,F13>='00_Control'!B19),"SCALE", IF(F13<='00_Control'!B20,"KILL","WATCH")) -> SCALE
A14: PMax | B14: Headline_B | C14: =SUMIFS('21_Model_Filtered'!F:F,'21_Model_Filtered'!C:C,$A14,'21_Model_Filtered'!E:E,$B14) -> 450.14 | D14: =SUMIFS('21_Model_Filtered'!J:J,'21_Model_Filtered'!C:C,$A14,'21_Model_Filtered'!E:E,$B14) -> 76 | E14: =SUMIFS('21_Model_Filtered'!K:K,'21_Model_Filtered'!C:C,$A14,'21_Model_Filtered'!E:E,$B14) -> 2825.97 | F14: =IFERROR(E14/C14,0) -> 6.2779802 | G14: =IFERROR(C14/D14,0) -> 5.9228947 | H14: =IFERROR( SUMIFS('21_Model_Filtered'!H:H,'21_Model_Filtered'!C:C,$A14,'21_Model_Filtered'!E:E,$B14) / SUMIFS('21_Model_Filtered'!G:G,'21_Model_Filtered'!C:C,$A14,'21_Model_Filtered'!E:E,$B14),0) -> 0.079199735 | I14: =IF(AND(C14>='00_Control'!B18,D14>='00_Control'!B19,F14>='00_Control'!B20),"SCALE", IF(F14<='00_Control'!B21,"KILL","WATCH")) -> SCALE
... A19: Search_Brand | B19: Headline_A | C19: =SUMIFS('21_Model_Filtered'!F:F,'21_Model_Filtered'!C:C,$A19,'21_Model_Filtered'!E:E,$B19) -> 352.29 | D19: =SUMIFS('21_Model_Filtered'!J:J,'21_Model_Filtered'!C:C,$A19,'21_Model_Filtered'!E:E,$B19) -> 44 | E19: =SUMIFS('21_Model_Filtered'!K:K,'21_Model_Filtered'!C:C,$A19,'21_Model_Filtered'!E:E,$B19) -> 2999.64 | F19: =IFERROR(E19/C19,0) -> 8.5146896 | G19: =IFERROR(C19/D19,0) -> 8.0065909 | H19: =IFERROR( SUMIFS('21_Model_Filtered'!H:H,'21_Model_Filtered'!C:C,$A19,'21_Model_Filtered'!E:E,$B19) / SUMIFS('21_Model_Filtered'!G:G,'21_Model_Filtered'!C:C,$A19,'21_Model_Filtered'!E:E,$B19),0) -> 0.11407094 | I19: =IF(AND(C19>='00_Control'!B23,D19>='00_Control'!B24,F19>='00_Control'!B25),"SCALE", IF(F19<='00_Control'!B26,"KILL","WATCH")) -> SCALE

Sheet 32_Product_Perf
A1: Product_Title | B1: Units_Sold | C1: Gross_Sales | D1: Discounts | E1: Refunds | F1: Net_Revenue | G1: AOV | H1: Decision
A2: {=_xlfn.UNIQUE(_xlfn._xlws.FILTER('03_Raw_Shopify'!D2:D10000,'03_Raw_Shopify'!D2:D10000<>""))} -> Collagen | B2: =SUMIFS('03_Raw_Shopify'!E:E,'03_Raw_Shopify'!D:D,$A2) -> 40 | C2: =SUMIFS('03_Raw_Shopify'!F:F,'03_Raw_Shopify'!D:D,$A2) -> 2374.98 | D2: =SUMIFS('03_Raw_Shopify'!G:G,'03_Raw_Shopify'!D:D,$A2) -> 254.14 | E2: =SUMIFS('03_Raw_Shopify'!H:H,'03_Raw_Shopify'!D:D,$A2) -> 94.36 | F2: =SUMIFS('03_Raw_Shopify'!I:I,'03_Raw_Shopify'!D:D,$A2) -> 2026.48 | G2: =IFERROR(F2/B2,0) -> 50.662 | H2: =IF(F2>2000,"HIGH PERFORMER", IF(F2<500,"LOW PERFORMER","AVERAGE")) -> HIGH PERFORMER
A3: Vitamin C | B3: =SUMIFS('03_Raw_Shopify'!E:E,'03_Raw_Shopify'!D:D,$A3) -> 45 | C3: =SUMIFS('03_Raw_Shopify'!F:F,'03_Raw_Shopify'!D:D,$A3) -> 2634.08 | D3: =SUMIFS('03_Raw_Shopify'!G:G,'03_Raw_Shopify'!D:D,$A3) -> 196.13 | E3: =SUMIFS('03_Raw_Shopify'!H:H,'03_Raw_Shopify'!D:D,$A3) -> 102.05 | F3: =SUMIFS('03_Raw_Shopify'!I:I,'03_Raw_Shopify'!D:D,$A3) -> 2335.9 | G3: =IFERROR(F3/B3,0) -> 51.908889 | H3: =IF(F3>2000,"HIGH PERFORMER", IF(F3<500,"LOW PERFORMER","AVERAGE")) -> HIGH PERFORMER
A4: Magnesium | B4: =SUMIFS('03_Raw_Shopify'!E:E,'03_Raw_Shopify'!D:D,$A4) -> 47 | C4: =SUMIFS('03_Raw_Shopify'!F:F,'03_Raw_Shopify'!D:D,$A4) -> 3245.22 | D4: =SUMIFS('03_Raw_Shopify'!G:G,'03_Raw_Shopify'!D:D,$A4) -> 233.28 | E4: =SUMIFS('03_Raw_Shopify'!H:H,'03_Raw_Shopify'!D:D,$A4) -> 135.71 | F4: =SUMIFS('03_Raw_Shopify'!I:I,'03_Raw_Shopify'!D:D,$A4) -> 2876.23 | G4: =IFERROR(F4/B4,0) -> 61.196383 | H4: =IF(F4>2000,"HIGH PERFORMER", IF(F4<500,"LOW PERFORMER","AVERAGE")) -> HIGH PERFORMER
A5: Protein Powder | B5: =SUMIFS('03_Raw_Shopify'!E:E,'03_Raw_Shopify'!D:D,$A5) -> 39 | C5: =SUMIFS('03_Raw_Shopify'!F:F,'03_Raw_Shopify'!D:D,$A5) -> 2071.02 | D5: =SUMIFS('03_Raw_Shopify'!G:G,'03_Raw_Shopify'!D:D,$A5) -> 171.85 | E5: =SUMIFS('03_Raw_Shopify'!H:H,'03_Raw_Shopify'!D:D,$A5) -> 82.95 | F5: =SUMIFS('03_Raw_Shopify'!I:I,'03_Raw_Shopify'!D:D,$A5) -> 1816.22 | G5: =IFERROR(F5/B5,0) -> 46.569744 | H5: =IF(F5>2000,"HIGH PERFORMER", IF(F5<500,"LOW PERFORMER","AVERAGE")) -> AVERAGE
A6: Omega 3 | B6: =SUMIFS('03_Raw_Shopify'!E:E,'03_Raw_Shopify'!D:D,$A6) -> 23 | C6: =SUMIFS('03_Raw_Shopify'!F:F,'03_Raw_Shopify'!D:D,$A6) -> 1388.18 | D6: =SUMIFS('03_Raw_Shopify'!G:G,'03_Raw_Shopify'!D:D,$A6) -> 77.66 | E6: =SUMIFS('03_Raw_Shopify'!H:H,'03_Raw_Shopify'!D:D,$A6) -> 62.77 | F6: =SUMIFS('03_Raw_Shopify'!I:I,'03_Raw_Shopify'!D:D,$A6) -> 1247.75 | G6: =IFERROR(F6/B6,0) -> 54.25 | H6: =IF(F6>2000,"HIGH PERFORMER", IF(F6<500,"LOW PERFORMER","AVERAGE")) -> AVERAGE

Sheet 40_Executive_Dashboard
B2: Total Spend | C2: Total Revenue | D2: Total Purchases | E2: Overall ROAS
B3: =SUM('21_Model_Filtered'!F:F) -> 15834.67 | C3: =SUM('21_Model_Filtered'!K:K) -> 83534.28 | D3: =SUM('21_Model_Filtered'!J:J) -> 2362 | E3: =C3/B3 -> 5.2754039
B6: Top Campaign | D6: Top Product | F6: Units Sold
B7: =INDEX('30_Campaign_Perf'!A:A,MATCH(MAX('30_Campaign_Perf'!E:E),'30_Campaign_Perf'!E:E,0)) -> Campaign_C | D7: =INDEX('32_Product_Perf'!A:A,MATCH(MAX('32_Product_Perf'!F:F),'32_Product_Perf'!F:F,0)) -> Magnesium | F7: =SUM('32_Product_Perf'!B:B) -> 194
B10: Date | C10: Revenue
B11: {=_xlfn.UNIQUE('21_Model_Filtered'!A2:A10000)} -> 46037 | C11: =SUMIFS('21_Model_Filtered'!K:K,'21_Model_Filtered'!A:A,B11) -> 4788.86
B12: 46038 | C12: =SUMIFS('21_Model_Filtered'!K:K,'21_Model_Filtered'!A:A,B12) -> 5707.91
B13: 46039 | C13: =SUMIFS('21_Model_Filtered'!K:K,'21_Model_Filtered'!A:A,B13) -> 6211.97
B14: 46040 | C14: =SUMIFS('21_Model_Filtered'!K:K,'21_Model_Filtered'!A:A,B14) -> 7367.29
B15: 46041 | C15: =SUMIFS('21_Model_Filtered'!K:K,'21_Model_Filtered'!A:A,B15) -> 4014.37
B16: 46042 | C16: =SUMIFS('21_Model_Filtered'!K:K,'21_Model_Filtered'!A:A,B16) -> 5120.93
B17: 46043 | C17: =SUMIFS('21_Model_Filtered'!K:K,'21_Model_Filtered'!A:A,B17) -> 4871.12
B18: 46044 | C18: =SUMIFS('21_Model_Filtered'!K:K,'21_Model_Filtered'!A:A,B18) -> 5682.76
B19: 46045 | C19: =SUMIFS('21_Model_Filtered'!K:K,'21_Model_Filtered'!A:A,B19) -> 5012
B20: 46046 | C20: =SUMIFS('21_Model_Filtered'!K:K,'21_Model_Filtered'!A:A,B20) -> 4502.74
B21: 46047 | C21: =SUMIFS('21_Model_Filtered'!K:K,'21_Model_Filtered'!A:A,B21) -> 5877.33
B22: 46048 | C22: =SUMIFS('21_Model_Filtered'!K:K,'21_Model_Filtered'!A:A,B22) -> 3865.75
B23: 46049 | C23: =SUMIFS('21_Model_Filtered'!K:K,'21_Model_Filtered'!A:A,B23) -> 7489.53
... B27: 0 | C27: =SUMIFS('21_Model_Filtered'!K:K,'21_Model_Filtered'!A:A,B27) -> 0
